afplot/__init__.py
afplot/afplot.py
afplot/cli.py
afplot/region.py
afplot/utils.py
afplot/variation.py
afplot/whole_genome.py
afplot-0.2.1.dist-info/DESCRIPTION.rst
afplot-0.2.1.dist-info/METADATA
afplot-0.2.1.dist-info/RECORD
afplot-0.2.1.dist-info/WHEEL
afplot-0.2.1.dist-info/entry_points.txt
afplot-0.2.1.dist-info/metadata.json
afplot-0.2.1.dist-info/top_level.txt
