Metadata-Version: 2.0
Name: afplot
Version: 0.2.1
Summary: Plot allele frequencies in VCF files
Home-page: https://github.com/sndrtj/afplot
Author: Sander Bollen
Author-email: a.h.b.bollen@lumc.nl
License: MIT
Platform: UNKNOWN
Classifier: Topic :: Scientific/Engineering :: Bio-Informatics
Requires-Dist: click
Requires-Dist: matplotlib
Requires-Dist: numpy
Requires-Dist: pandas
Requires-Dist: progressbar2
Requires-Dist: pysam
Requires-Dist: pyvcf
Requires-Dist: seaborn
